django_capture_on_commit_callbacks/__init__.py
django_capture_on_commit_callbacks/py.typed
django_capture_on_commit_callbacks-1.11.0.dist-info/LICENSE
django_capture_on_commit_callbacks-1.11.0.dist-info/METADATA
django_capture_on_commit_callbacks-1.11.0.dist-info/WHEEL
django_capture_on_commit_callbacks-1.11.0.dist-info/top_level.txt
django_capture_on_commit_callbacks-1.11.0.dist-info/RECORD
