Metadata-Version: 2.1
Name: django-capture-on-commit-callbacks
Version: 1.11.0
Summary: Capture and make assertions on transaction.on_commit() callbacks.
Home-page: https://github.com/adamchainz/django-capture-on-commit-callbacks
Author: Adam Johnson
Author-email: me@adamj.eu
License: MIT
Project-URL: Changelog, https://github.com/adamchainz/django-capture-on-commit-callbacks/blob/main/HISTORY.rst
Project-URL: Twitter, https://twitter.com/adamchainz
Keywords: Django
Platform: UNKNOWN
Classifier: Development Status :: 5 - Production/Stable
Classifier: Framework :: Django :: 3.2
Classifier: Framework :: Django :: 4.0
Classifier: Intended Audience :: Developers
Classifier: License :: OSI Approved :: MIT License
Classifier: Natural Language :: English
Classifier: Operating System :: OS Independent
Classifier: Programming Language :: Python :: 3 :: Only
Classifier: Programming Language :: Python :: 3
Classifier: Programming Language :: Python :: 3.7
Classifier: Programming Language :: Python :: 3.8
Classifier: Programming Language :: Python :: 3.9
Classifier: Programming Language :: Python :: 3.10
Requires-Python: >=3.7
License-File: LICENSE
